MANIFEST.in
README.rst
setup.py
basic_models_behaviors/__init__.py
basic_models_behaviors/managers.py
basic_models_behaviors/models.py
django_basic_models_behaviors.egg-info/PKG-INFO
django_basic_models_behaviors.egg-info/SOURCES.txt
django_basic_models_behaviors.egg-info/dependency_links.txt
django_basic_models_behaviors.egg-info/not-zip-safe
django_basic_models_behaviors.egg-info/top_level.txt
docs/Makefile
docs/conf.py
docs/index.rst