Metadata-Version: 1.1
Name: django-basic-models-behaviors
Version: 0.6.0
Summary: Tiny app to provide basic behaviors for django models.
Home-page: https://github.com/wo0dyn/django-basic-models-behaviors
Author: Nicolas Dubois
Author-email: nicolas.c.dubois@gmail.com
License: MIT License
Keywords: django
Platform: any
Classifier: Development Status :: 4 - Beta
Classifier: Environment :: Web Environment
Classifier: Framework :: Django
Classifier: Intended Audience :: Developers
Classifier: License :: OSI Approved :: MIT License
Classifier: Operating System :: OS Independent
Classifier: Programming Language :: Python
Classifier: Programming Language :: Python :: 2
Classifier: Programming Language :: Python :: 2.7
Classifier: Programming Language :: Python :: 3
Classifier: Programming Language :: Python :: 3.2
Classifier: Programming Language :: Python :: 3.3
Classifier: Programming Language :: Python :: 3.4
